pynwjs/__init__.py
pynwjs/nwjs.py
pynwjs-0.0.3.dist-info/LICENSE
pynwjs-0.0.3.dist-info/METADATA
pynwjs-0.0.3.dist-info/WHEEL
pynwjs-0.0.3.dist-info/top_level.txt
pynwjs-0.0.3.dist-info/RECORD
