Metadata-Version: 2.1
Name: pynwjs
Version: 0.0.3
Summary: Use nwjs as GUI in Python
Home-page: https://github.com/pschillinger/pynwjs
Author: Philipp Schillinger
Author-email: schillin@kth.se
License: BSD 3
Platform: UNKNOWN
Classifier: Development Status :: 3 - Alpha
Classifier: License :: OSI Approved :: BSD License
